eiger/__init__.py
eiger/py.typed
eiger-1.0.0a0.dist-info/LICENSE
eiger-1.0.0a0.dist-info/METADATA
eiger-1.0.0a0.dist-info/WHEEL
eiger-1.0.0a0.dist-info/RECORD
